odoo9_addon_web_selenium-9.0.1.0.2-py2.7-nspkg.pth
odoo9_addon_web_selenium-9.0.1.0.2.dist-info/DESCRIPTION.rst
odoo9_addon_web_selenium-9.0.1.0.2.dist-info/METADATA
odoo9_addon_web_selenium-9.0.1.0.2.dist-info/RECORD
odoo9_addon_web_selenium-9.0.1.0.2.dist-info/WHEEL
odoo9_addon_web_selenium-9.0.1.0.2.dist-info/metadata.json
odoo9_addon_web_selenium-9.0.1.0.2.dist-info/namespace_packages.txt
odoo9_addon_web_selenium-9.0.1.0.2.dist-info/top_level.txt
odoo_addons/web_selenium/README.rst
odoo_addons/web_selenium/__init__.py
odoo_addons/web_selenium/__openerp__.py
odoo_addons/web_selenium/static/src/xml/base_ext.xml
