Metadata-Version: 2.0
Name: odoo9-addon-web-selenium
Version: 9.0.1.0.2
Summary: Record your testcases with Selenium
Home-page: http://www.brain-tec.ch
Author: Andreas Stauder
Author-email: andreas.stauder@brain-tec.ch
License: UNKNOWN
Platform: UNKNOWN
Requires-Dist: odoo (<9.1a,>=9.0a)
